pico_celery/__init__.py
pico_celery/_version.py
pico_celery/client.py
pico_celery/config.py
pico_celery/decorators.py
pico_celery/factory.py
pico_celery/registrar.py
pico_celery-0.1.1.dist-info/licenses/LICENSE
pico_celery-0.1.1.dist-info/METADATA
pico_celery-0.1.1.dist-info/WHEEL
pico_celery-0.1.1.dist-info/top_level.txt
pico_celery-0.1.1.dist-info/RECORD
