Metadata-Version: 2.4
Name: pico-celery
Version: 0.1.1
Summary: Async-first Celery integration for Pico-IoC. Enables defining Celery tasks as async methods on IoC-managed components, with automatic discovery, dependency injection, and container-scoped execution.
Author-email: David Perez Cabrera <dperezcabrera@gmail.com>
License: MIT License
Project-URL: Homepage, https://github.com/dperezcabrera/pico-celery
Project-URL: Repository, https://github.com/dperezcabrera/pico-celery
Project-URL: Issue Tracker, https://github.com/dperezcabrera/pico-celery/issues
Keywords: ioc,di,dependency injection,celery,inversion of control,spring boot,controller
Classifier: Development Status :: 4 - Beta
Classifier: Framework :: AsyncIO
Classifier: Topic :: System :: Distributed Computing
Classifier: Topic :: Software Development :: Libraries :: Python Modules
Classifier: Programming Language :: Python :: 3
Classifier: Programming Language :: Python :: 3 :: Only
Classifier: Programming Language :: Python :: 3.10
Classifier: Programming Language :: Python :: 3.11
Classifier: Programming Language :: Python :: 3.12
Classifier: Programming Language :: Python :: 3.13
Classifier: Programming Language :: Python :: 3.14
Classifier: License :: OSI Approved :: MIT License
Classifier: Operating System :: OS Independent
Requires-Python: >=3.10
License-File: LICENSE
Requires-Dist: pico-ioc>=2.1.2
Requires-Dist: celery<6.0,>=5.3
Provides-Extra: session
Requires-Dist: starlette-session; extra == "session"
Provides-Extra: run
Requires-Dist: uvicorn[standard]; extra == "run"
Dynamic: license-file
